subjective_test/__init__.py
subjective_test/utilities.py
subjective_test-0.0.2.dist-info/LICENSE
subjective_test-0.0.2.dist-info/METADATA
subjective_test-0.0.2.dist-info/WHEEL
subjective_test-0.0.2.dist-info/top_level.txt
subjective_test-0.0.2.dist-info/RECORD
