Metadata-Version: 2.1
Name: subjective-test
Version: 0.0.2
Summary: Transforming the Mean Opinion Scores (MOS) values given their 95% Confidence Intervals to safely use rank based statictial techniques.
Home-page: https://github.com/babaknaderi/MOS-transformation
Author: Babak Naderi
Author-email: bnaderi9@gmail.com
License: UNKNOWN
Platform: UNKNOWN
Classifier: Programming Language :: Python :: 3
Classifier: License :: OSI Approved :: MIT License
Classifier: Operating System :: OS Independent
Requires-Python: >=3.6
